{"text": "(\\ She stand still Time be moving past so fast, ain't got a chance And now my life heavy monetized, that's how I feel She's my dream, so you live your life And I'm guilty sad Cause you just might, might, I am, cause you just might, cause you just might, I am, cause you just might, cause you just might, cause you just might, I am And you cryin' past, and you know that I'm fuckin' all night, and you", "segments": [{"id": 0, "seek": 0, "start": 0.0, "end": 0.86, "text": "(\\", "tokens": [50363, 38016, 51642], "temperature": 1.0, "avg_logprob": -3.296870803833008, "compression_ratio": 0.2, "no_speech_prob": 0.00766921928152442, "words": [{"word": "(\\", "start": 0.0, "end": 0.86, "probability": 8.918373595179219e-08}]}, {"id": 1, "seek": 86, "start": 4.499999999999997, "end": 10.44, "text": " She stand still Time be moving past so fast, ain't got a chance", "tokens": [50363, 1375, 1302, 991, 3862, 307, 3867, 1613, 523, 3049, 11, 18959, 470, 1392, 257, 2863, 50863], "temperature": 0.0, "avg_logprob": -0.6789741516113281, "compression_ratio": 1.2954545454545454, "no_speech_prob": 0.6891894936561584, "words": [{"word": " She", "start": 4.499999999999997, "end": 5.059999999999999, "probability": 0.07330811768770218}, {"word": " stand", "start": 5.059999999999999, "end": 5.62, "probability": 0.19166021049022675}, {"word": " still", "start": 5.62, "end": 6.28, "probability": 0.5998053550720215}, {"word": " Time", "start": 6.28, "end": 7.68, "probability": 0.7235178351402283}, {"word": " be", "start": 7.68, "end": 7.88, "probability": 0.5214238166809082}, {"word": " moving", "start": 7.88, "end": 8.16, "probability": 0.28369081020355225}, {"word": " past", "start": 8.16, "end": 8.46, "probability": 0.21446458995342255}, {"word": " so", "start": 8.46, "end": 8.82, "probability": 0.7850611805915833}, {"word": " fast,", "start": 8.82, "end": 9.16, "probability": 0.5164292454719543}, {"word": " ain't", "start": 9.16, "end": 9.62, "probability": 0.6666007339954376}, {"word": " got", "start": 9.62, "end": 9.86, "probability": 0.5349618792533875}, {"word": " a", "start": 9.86, "end": 9.96, "probability": 0.20898231863975525}, {"word": " chance", "start": 9.96, "end": 10.44, "probability": 0.3677692115306854}]}, {"id": 2, "seek": 86, "start": 11.32, "end": 14.64, "text": " And now my life heavy monetized, that's how I feel", "tokens": [50863, 843, 783, 616, 1204, 4334, 32153, 1143, 11, 326, 338, 703, 314, 1254, 51113], "temperature": 0.0, "avg_logprob": -0.6789741516113281, "compression_ratio": 1.2954545454545454, "no_speech_prob": 0.6891894936561584, "words": [{"word": " And", "start": 11.32, "end": 11.88, "probability": 0.5906079411506653}, {"word": " now", "start": 11.88, "end": 12.02, "probability": 0.47912123799324036}, {"word": " my", "start": 12.02, "end": 12.2, "probability": 0.9692941308021545}, {"word": " life", "start": 12.2, "end": 12.46, "probability": 0.99530029296875}, {"word": " heavy", "start": 12.46, "end": 12.86, "probability": 0.7946247458457947}, {"word": " monetized,", "start": 12.86, "end": 13.64, "probability": 0.8586432933807373}, {"word": " that's", "start": 13.64, "end": 14.14, "probability": 0.9444409608840942}, {"word": " how", "start": 14.14, "end": 14.24, "probability": 0.9933764338493347}, {"word": " I", "start": 14.24, "end": 14.4, "probability": 0.8783295750617981}, {"word": " feel", "start": 14.4, "end": 14.64, "probability": 0.8823376297950745}]}, {"id": 3, "seek": 86, "start": 15.779999999999998, "end": 19.9, "text": " She's my dream, so you live your life And I'm guilty sad", "tokens": [51113, 1375, 338, 616, 4320, 11, 523, 345, 2107, 534, 1204, 843, 314, 1101, 6717, 6507, 51313], "temperature": 0.0, "avg_logprob": -0.6789741516113281, "compression_ratio": 1.2954545454545454, "no_speech_prob": 0.6891894936561584, "words": [{"word": " She's", "start": 15.779999999999998, "end": 16.34, "probability": 0.3874678760766983}, {"word": " my", "start": 16.34, "end": 16.5, "probability": 0.47929462790489197}, {"word": " dream,", "start": 16.5, "end": 16.72, "probability": 0.9169543385505676}, {"word": " so", "start": 16.8, "end": 17.04, "probability": 0.8828316330909729}, {"word": " you", "start": 17.04, "end": 17.2, "probability": 0.9706951975822449}, {"word": " live", "start": 17.2, "end": 17.38, "probability": 0.48980042338371277}, {"word": " your", "start": 17.38, "end": 17.58, "probability": 0.9905175566673279}, {"word": " life", "start": 17.58, "end": 18.08, "probability": 0.984224796295166}, {"word": " And", "start": 18.08, "end": 18.36, "probability": 0.37465807795524597}, {"word": " I'm", "start": 18.36, "end": 18.82, "probability": 0.8231464922428131}, {"word": " guilty", "start": 18.82, "end": 18.98, "probability": 0.7362703084945679}, {"word": " sad", "start": 18.98, "end": 19.9, "probability": 0.43185216188430786}]}, {"id": 4, "seek": 1990, "start": 19.9, "end": 31.04, "text": " Cause you just might, might, I am, cause you just might, cause you just might, I am, cause you just might, cause you just might, cause you just might, I am", "tokens": [50363, 24228, 345, 655, 1244, 11, 1244, 11, 314, 716, 11, 2728, 345, 655, 1244, 11, 2728, 345, 655, 1244, 11, 314, 716, 11, 2728, 345, 655, 1244, 11, 2728, 345, 655, 1244, 11, 2728, 345, 655, 1244, 11, 314, 716, 50911], "temperature": 0.4, "avg_logprob": -0.462847166794997, "compression_ratio": 2.34375, "no_speech_prob": 0.2934659719467163, "words": [{"word": " Cause", "start": 19.9, "end": 20.34, "probability": 0.3665628731250763}, {"word": " you", "start": 20.34, "end": 20.5, "probability": 0.845812201499939}, {"word": " just", "start": 20.5, "end": 20.76, "probability": 0.7319297194480896}, {"word": " might,", "start": 20.76, "end": 21.12, "probability": 0.3503984212875366}, {"word": " might,", "start": 21.16, "end": 21.6, "probability": 0.9513874650001526}, {"word": " I", "start": 21.6, "end": 21.98, "probability": 0.608959972858429}, {"word": " am,", "start": 21.98, "end": 22.26, "probability": 0.34953662753105164}, {"word": " cause", "start": 22.4, "end": 22.52, "probability": 0.6513658761978149}, {"word": " you", "start": 22.52, "end": 22.76, "probability": 0.8699246644973755}, {"word": " just", "start": 22.76, "end": 23.06, "probability": 0.9573065042495728}, {"word": " might,", "start": 23.06, "end": 23.5, "probability": 0.6063357591629028}, {"word": " cause", "start": 23.76, "end": 24.26, "probability": 0.18090736865997314}, {"word": " you", "start": 24.26, "end": 24.8, "probability": 0.9907507300376892}, {"word": " just", "start": 24.8, "end": 25.12, "probability": 0.9901521801948547}, {"word": " might,", "start": 25.12, "end": 25.66, "probability": 0.5889862775802612}, {"word": " I", "start": 25.68, "end": 26.32, "probability": 0.7422195672988892}, {"word": " am,", "start": 26.32, "end": 26.6, "probability": 0.9901819825172424}, {"word": " cause", "start": 26.6, "end": 26.82, "probability": 0.9811756014823914}, {"word": " you", "start": 26.82, "end": 26.98, "probability": 0.9943108558654785}, {"word": " just", "start": 26.98, "end": 27.28, "probability": 0.992634117603302}, {"word": " might,", "start": 27.28, "end": 27.94, "probability": 0.925812840461731}, {"word": " cause", "start": 28.1, "end": 28.98, "probability": 0.7345795035362244}, {"word": " you", "start": 28.98, "end": 29.14, "probability": 0.9964459538459778}, {"word": " just", "start": 29.14, "end": 29.48, "probability": 0.9921247363090515}, {"word": " might,", "start": 29.48, "end": 29.82, "probability": 0.9637958407402039}, {"word": " cause", "start": 29.82, "end": 29.82, "probability": 0.13056883215904236}, {"word": " you", "start": 29.82, "end": 29.82, "probability": 0.9946560859680176}, {"word": " just", "start": 29.82, "end": 29.82, "probability": 0.9955534338951111}, {"word": " might,", "start": 29.82, "end": 29.98, "probability": 0.9799565076828003}, {"word": " I", "start": 30.52, "end": 30.68, "probability": 0.6007445454597473}, {"word": " am", "start": 30.68, "end": 31.04, "probability": 0.1483263373374939}]}, {"id": 5, "seek": 1990, "start": 31.04, "end": 34.98, "text": " And you cryin' past, and you know that I'm fuckin' all night, and you", "tokens": [50911, 843, 345, 3960, 259, 6, 1613, 11, 290, 345, 760, 326, 314, 1101, 46733, 6, 477, 1755, 11, 290, 345, 51115], "temperature": 0.4, "avg_logprob": -0.462847166794997, "compression_ratio": 2.34375, "no_speech_prob": 0.2934659719467163, "words": [{"word": " And", "start": 31.04, "end": 31.12, "probability": 0.001103427610360086}, {"word": " you", "start": 31.12, "end": 31.22, "probability": 0.6577135324478149}, {"word": " cryin'", "start": 31.22, "end": 31.74, "probability": 0.18126186728477478}, {"word": " past,", "start": 31.98, "end": 32.08, "probability": 0.4221237301826477}, {"word": " and", "start": 32.62, "end": 32.72, "probability": 0.6981704831123352}, {"word": " you", "start": 32.72, "end": 32.88, "probability": 0.9668166637420654}, {"word": " know", "start": 32.88, "end": 33.04, "probability": 0.9899175763130188}, {"word": " that", "start": 33.04, "end": 33.18, "probability": 0.9181995987892151}, {"word": " I'm", "start": 33.18, "end": 33.4, "probability": 0.9358985424041748}, {"word": " fuckin'", "start": 33.4, "end": 33.66, "probability": 0.7746938467025757}, {"word": " all", "start": 33.88, "end": 33.92, "probability": 0.6317552924156189}, {"word": " night,", "start": 33.92, "end": 34.26, "probability": 0.9888514876365662}, {"word": " and", "start": 34.76, "end": 34.84, "probability": 0.7263940572738647}, {"word": " you", "start": 34.84, "end": 34.98, "probability": 0.9687382578849792}]}], "language": "en"}